Cricket_Squad_Scraper/__init__.py
Cricket_Squad_Scraper/scraper.py
Cricket_Squad_Scraper-0.1.dist-info/METADATA
Cricket_Squad_Scraper-0.1.dist-info/WHEEL
Cricket_Squad_Scraper-0.1.dist-info/top_level.txt
Cricket_Squad_Scraper-0.1.dist-info/RECORD
